LICENSE.txt
MANIFEST.in
README.rst
setup.py
PyTPM.egg-info/PKG-INFO
PyTPM.egg-info/SOURCES.txt
PyTPM.egg-info/dependency_links.txt
PyTPM.egg-info/top_level.txt
data/aop.py
data/hip.py
data/hip_full.py
data/hip_icrs.py
data/hip_readme.txt
data/map.py
data/ndwfs.py
data/read_data.py
data/slalib_convert_hip.py
data/slalib_convert_ndwfs.py
data/summary_test_slalib.py
doc/Makefile
doc/astrometry.rst
doc/comparisons.rst
doc/conf.py
doc/conversions.rst
doc/data_structures.rst
doc/functions.rst
doc/index.rst
doc/installation.rst
doc/make.bat
doc/TPM/leap_seconds.txt
doc/TPM/tpm.pdf
doc/_templates/class.rst
doc/examples/Makefile
doc/examples/conversion_example.c
doc/examples/conversion_example.py
doc/examples/conversions.py
doc/examples/hip_convert.py
doc/examples/hip_full.py
doc/examples/hip_full.txt
doc/examples/read_data.pyc
pytpm/__init__.py
pytpm/tests/__init__.py
pytpm/tests/test_conversions_with_pm.py
pytpm/tests/test_convert.py
pytpm/tests/test_pytpm_astro.py
pytpm/tests/test_pytpm_times.py
pytpm/tests/test_pytpm_tpm.py
pytpm/tests/test_pytpm_utils.py
pytpm/tests/test_pytpm_vec.py
pytpm/tests/test_slalib.py
pytpm/tests/c_tests/Makefile
pytpm/tests/c_tests/aberrate_test.c
pytpm/tests/c_tests/azel2hadec_test.c
pytpm/tests/c_tests/cat2v6_v62cat_test.c
pytpm/tests/c_tests/d2d_test.c
pytpm/tests/c_tests/dms2dms_test.c
pytpm/tests/c_tests/eccentricity_test.c
pytpm/tests/c_tests/ecl2equ_test.c
pytpm/tests/c_tests/ellab_test.c
pytpm/tests/c_tests/equ2ecl_test.c
pytpm/tests/c_tests/equ2gal_test.c
pytpm/tests/c_tests/eterms_test.c
pytpm/tests/c_tests/evp_test.c
pytpm/tests/c_tests/fk425_test.c
pytpm/tests/c_tests/fmt_alpha_test.c
pytpm/tests/c_tests/fmt_d_test.c
pytpm/tests/c_tests/fmt_delta_test.c
pytpm/tests/c_tests/fmt_h.c
pytpm/tests/c_tests/fmt_j_test.c
pytpm/tests/c_tests/fmt_jd_test.c
pytpm/tests/c_tests/fmt_r_test.c
pytpm/tests/c_tests/fmt_y_test.c
pytpm/tests/c_tests/fmt_ymd_raw_test.c
pytpm/tests/c_tests/fmt_ymd_test.c
pytpm/tests/c_tests/gal2equ_test.c
pytpm/tests/c_tests/geod2geoc_test.c
pytpm/tests/c_tests/h2h_test.c
pytpm/tests/c_tests/hipicrsep1991_EclJ2000ep2000.txt
