Metadata-Version: 1.0
Name: PyTPM
Version: 0.7.1
Summary: Python interface to Telescope Pointing Machine C library.
Home-page: https://github.com/phn/pytpm
Author: Prasanth Nair
Author-email: prasanthhn@gmail.com
License: BSD
Platform: UNKNOWN
Classifier: Development Status :: 6 - Mature
Classifier: Intended Audience :: Science/Research
Classifier: License :: OSI Approved :: BSD License
Classifier: Topic :: Scientific/Engineering :: Astronomy
